{
  "indexes": [
    {
      "collectionGroup": "leaderboard",
      "queryScope": "COLLECTION",
      "fields": [
        {
          "fieldPath": "kills",
          "order": "DESCENDING"
        },
        {
          "fieldPath": "timestamp",
          "order": "DESCENDING"
        }
      ]
    },
    {
      "collectionGroup": "rooms",
      "queryScope": "COLLECTION",
      "fields": [
        {
          "fieldPath": "status",
          "order": "ASCENDING"
        },
        {
          "fieldPath": "createdAt",
          "order": "DESCENDING"
        }
      ]
    }
  ],
  "fieldOverrides": []
}
